README.md
setup.py
gym_kuhn_poker/__init__.py
gym_kuhn_poker.egg-info/PKG-INFO
gym_kuhn_poker.egg-info/SOURCES.txt
gym_kuhn_poker.egg-info/dependency_links.txt
gym_kuhn_poker.egg-info/requires.txt
gym_kuhn_poker.egg-info/top_level.txt
gym_kuhn_poker/envs/__init__.py
gym_kuhn_poker/envs/kuhn_poker_env.py
gym_kuhn_poker/envs/one_hot_space.py