Metadata-Version: 1.0
Name: gym-kuhn-poker
Version: 0.1
Summary: OpenAI gym environment for Kuhn poker
Home-page: https://github.com/Danielhp95/gym-kuhn-poker
Author: Sarios
Author-email: madness@xcape.com
License: UNKNOWN
Platform: UNKNOWN
